pyeas/__init__.py
pyeas/_cmaes.py
pyeas/_de.py
pyeas/_oaies.py
pyeas/_pagetest.py
pyeas/_plotter.py
pyeas/_population_scaling.py
tests/__init__.py
tests/my_test.py
pyeas-0.2.0.dist-info/LICENSE
pyeas-0.2.0.dist-info/METADATA
pyeas-0.2.0.dist-info/WHEEL
pyeas-0.2.0.dist-info/top_level.txt
pyeas-0.2.0.dist-info/RECORD
