Metadata-Version: 2.1
Name: pyeas
Version: 0.2.0
Summary: Implements Evolutionary Algorithms and tools
Home-page: https://github.com/benedictjones/pyeas
Author: benedictjones
License: BSD License (BSD-3-Clause)
Keywords: python,Differential Evolution,DE,OpenAI Evolutionary Strategy,OpenAI-ES,CMAES,Page Trend Test
Platform: UNKNOWN
Requires-Dist: numpy
Requires-Dist: scipy
Requires-Dist: matplotlib
Requires-Dist: tqdm
